dlimg-0.1.10.data/scripts/dlimg
libdlimg/__init__.py
libdlimg/core.py
libdlimg/dlimg.py
libdlimg/error.py
libdlimg/lib.py
libdlimg/list.py
libdlimg/waiter.py
libdlimg/sites/__init__.py
libdlimg/sites/anysites.py
libdlimg/sites/bing.py
libdlimg/sites/google.py
libdlimg/sites/irasutoya.py
libdlimg/sites/tsundora.py
libdlimg/sites/unsplash.py
libdlimg/sites/wear.py
libdlimg/sites/yandere.py
dlimg-0.1.10.dist-info/METADATA
dlimg-0.1.10.dist-info/WHEEL
dlimg-0.1.10.dist-info/top_level.txt
dlimg-0.1.10.dist-info/RECORD
