Metadata-Version: 2.1
Name: dlimg
Version: 0.1.10
Summary: Fast image downloader
Home-page: https://github.com/shosatojp/fast-image-downloader
Author: shosatojp
Author-email: me@shosato.jp
License: UNKNOWN
Platform: UNKNOWN
Classifier: Programming Language :: Python :: 3
Classifier: License :: OSI Approved :: MIT License
Classifier: Operating System :: OS Independent
Requires-Python: >=3.6
Requires-Dist: aiofiles
Requires-Dist: aiohttp
Requires-Dist: bs4
Requires-Dist: lxml
Requires-Dist: requests
Requires-Dist: selenium
